[{"_id":"60d44cda8692f219bca1ed1e","time":1,"uplink":5,"downlink":9,"ue_list":[{"_id":"60d44cda8692f219bca1ed1f","enb_ue_id":0,"mme_ue_id":1,"rnti":2,"cells":[{"_id":"60d44cda8692f219bca1ed20","cell_id":0,"dl_bitrate":0,"ul_bitrate":10,"dl_tx":8,"ul_tx":1,"dl_retx":7,"ul_retx":9,"pucch1_snr":0,"pusch1_snr":4,"epre":1,"dl_mcs":1,"ul_mcs":0,"turbo_decoder_min":8,"turbo_decoder_avg":1,"turbo_decoder_max":3,"cqi":4,"ri":6},{"_id":"60d44cda8692f219bca1ed21","cell_id":0,"dl_bitrate":9,"ul_bitrate":8,"dl_tx":10,"ul_tx":0,"dl_retx":8,"ul_retx":5,"pucch1_snr":8,"pusch1_snr":9,"epre":1,"dl_mcs":1,"ul_mcs":6,"turbo_decoder_min":10,"turbo_decoder_avg":10,"turbo_decoder_max":0,"cqi":5,"ri":7},{"_id":"60d44cda8692f219bca1ed22","cell_id":1,"dl_bitrate":3,"ul_bitrate":10,"dl_tx":3,"ul_tx":9,"dl_retx":5,"ul_retx":8,"pucch1_snr":10,"pusch1_snr":0,"epre":7,"dl_mcs":8,"ul_mcs":0,"turbo_decoder_min":4,"turbo_decoder_avg":9,"turbo_decoder_max":9,"cqi":8,"ri":0}]},{"_id":"60d44cda8692f219bca1ed23","enb_ue_id":1,"mme_ue_id":1,"rnti":0,"cells":[{"_id":"60d44cda8692f219bca1ed24","cell_id":2,"dl_bitrate":2,"ul_bitrate":9,"dl_tx":10,"ul_tx":9,"dl_retx":1,"ul_retx":2,"pucch1_snr":9,"pusch1_snr":8,"epre":3,"dl_mcs":7,"ul_mcs":5,"turbo_decoder_min":8,"turbo_decoder_avg":3,"turbo_decoder_max":10,"cqi":1,"ri":3},{"_id":"60d44cda8692f219bca1ed25","cell_id":1,"dl_bitrate":8,"ul_bitrate":1,"dl_tx":5,"ul_tx":4,"dl_retx":10,"ul_retx":3,"pucch1_snr":8,"pusch1_snr":3,"epre":3,"dl_mcs":2,"ul_mcs":5,"turbo_decoder_min":10,"turbo_decoder_avg":1,"turbo_decoder_max":5,"cqi":10,"ri":2},{"_id":"60d44cda8692f219bca1ed26","cell_id":1,"dl_bitrate":6,"ul_bitrate":10,"dl_tx":3,"ul_tx":7,"dl_retx":9,"ul_retx":0,"pucch1_snr":1,"pusch1_snr":10,"epre":9,"dl_mcs":4,"ul_mcs":3,"turbo_decoder_min":4,"turbo_decoder_avg":3,"turbo_decoder_max":9,"cqi":1,"ri":3}]}],"mongo_time":"2021-06-24T09:14:02.396Z","__v":0},{"_id":"60d44cdb8692f219bca1ed28","time":4,"uplink":6,"downlink":3,"ue_list":[{"_id":"60d44cdb8692f219bca1ed29","enb_ue_id":1,"mme_ue_id":0,"rnti":2,"cells":[{"_id":"60d44cdb8692f219bca1ed2a","cell_id":0,"dl_bitrate":5,"ul_bitrate":5,"dl_tx":8,"ul_tx":2,"dl_retx":10,"ul_retx":6,"pucch1_snr":8,"pusch1_snr":4,"epre":9,"dl_mcs":0,"ul_mcs":10,"turbo_decoder_min":8,"turbo_decoder_avg":2,"turbo_decoder_max":1,"cqi":8,"ri":3},{"_id":"60d44cdb8692f219bca1ed2b","cell_id":0,"dl_bitrate":8,"ul_bitrate":10,"dl_tx":6,"ul_tx":7,"dl_retx":8,"ul_retx":2,"pucch1_snr":5,"pusch1_snr":8,"epre":6,"dl_mcs":7,"ul_mcs":7,"turbo_decoder_min":1,"turbo_decoder_avg":9,"turbo_decoder_max":6,"cqi":8,"ri":4},{"_id":"60d44cdb8692f219bca1ed2c","cell_id":2,"dl_bitrate":6,"ul_bitrate":6,"dl_tx":1,"ul_tx":3,"dl_retx":6,"ul_retx":7,"pucch1_snr":7,"pusch1_snr":6,"epre":2,"dl_mcs":2,"ul_mcs":9,"turbo_decoder_min":6,"turbo_decoder_avg":6,"turbo_decoder_max":4,"cqi":5,"ri":1}]},{"_id":"60d44cdb8692f219bca1ed2d","enb_ue_id":1,"mme_ue_id":2,"rnti":2,"cells":[{"_id":"60d44cdb8692f219bca1ed2e","cell_id":0,"dl_bitrate":3,"ul_bitrate":5,"dl_tx":0,"ul_tx":6,"dl_retx":5,"ul_retx":1,"pucch1_snr":2,"pusch1_snr":5,"epre":6,"dl_mcs":4,"ul_mcs":3,"turbo_decoder_min":5,"turbo_decoder_avg":1,"turbo_decoder_max":0,"cqi":6,"ri":7},{"_id":"60d44cdb8692f219bca1ed2f","cell_id":1,"dl_bitrate":10,"ul_bitrate":9,"dl_tx":2,"ul_tx":2,"dl_retx":6,"ul_retx":10,"pucch1_snr":8,"pusch1_snr":6,"epre":0,"dl_mcs":5,"ul_mcs":9,"turbo_decoder_min":1,"turbo_decoder_avg":8,"turbo_decoder_max":6,"cqi":6,"ri":0},{"_id":"60d44cdb8692f219bca1ed30","cell_id":2,"dl_bitrate":10,"ul_bitrate":10,"dl_tx":3,"ul_tx":8,"dl_retx":0,"ul_retx":10,"pucch1_snr":5,"pusch1_snr":8,"epre":1,"dl_mcs":0,"ul_mcs":1,"turbo_decoder_min":8,"turbo_decoder_avg":9,"turbo_decoder_max":0,"cqi":3,"ri":4}]}],"mongo_time":"2021-06-24T09:14:03.419Z","__v":0},{"_id":"60d44cdc8692f219bca1ed32","time":3,"uplink":6,"downlink":8,"ue_list":[{"_id":"60d44cdc8692f219bca1ed33","enb_ue_id":0,"mme_ue_id":1,"rnti":0,"cells":[{"_id":"60d44cdc8692f219bca1ed34","cell_id":1,"dl_bitrate":4,"ul_bitrate":7,"dl_tx":2,"ul_tx":5,"dl_retx":9,"ul_retx":10,"pucch1_snr":3,"pusch1_snr":4,"epre":6,"dl_mcs":4,"ul_mcs":8,"turbo_decoder_min":7,"turbo_decoder_avg":10,"turbo_decoder_max":5,"cqi":2,"ri":10},{"_id":"60d44cdc8692f219bca1ed35","cell_id":2,"dl_bitrate":5,"ul_bitrate":3,"dl_tx":4,"ul_tx":1,"dl_retx":3,"ul_retx":7,"pucch1_snr":8,"pusch1_snr":10,"epre":4,"dl_mcs":3,"ul_mcs":1,"turbo_decoder_min":0,"turbo_decoder_avg":9,"turbo_decoder_max":9,"cqi":6,"ri":0},{"_id":"60d44cdc8692f219bca1ed36","cell_id":0,"dl_bitrate":8,"ul_bitrate":4,"dl_tx":9,"ul_tx":2,"dl_retx":8,"ul_retx":3,"pucch1_snr":5,"pusch1_snr":5,"epre":10,"dl_mcs":7,"ul_mcs":5,"turbo_decoder_min":3,"turbo_decoder_avg":5,"turbo_decoder_max":0,"cqi":6,"ri":2}]},{"_id":"60d44cdc8692f219bca1ed37","enb_ue_id":1,"mme_ue_id":0,"rnti":2,"cells":[{"_id":"60d44cdc8692f219bca1ed38","cell_id":0,"dl_bitrate":9,"ul_bitrate":4,"dl_tx":9,"ul_tx":5,"dl_retx":0,"ul_retx":2,"pucch1_snr":7,"pusch1_snr":8,"epre":6,"dl_mcs":2,"ul_mcs":0,"turbo_decoder_min":2,"turbo_decoder_avg":8,"turbo_decoder_max":8,"cqi":4,"ri":7},{"_id":"60d44cdc8692f219bca1ed39","cell_id":1,"dl_bitrate":2,"ul_bitrate":1,"dl_tx":9,"ul_tx":10,"dl_retx":5,"ul_retx":0,"pucch1_snr":3,"pusch1_snr":2,"epre":2,"dl_mcs":1,"ul_mcs":10,"turbo_decoder_min":3,"turbo_decoder_avg":10,"turbo_decoder_max":3,"cqi":10,"ri":0},{"_id":"60d44cdc8692f219bca1ed3a","cell_id":1,"dl_bitrate":10,"ul_bitrate":4,"dl_tx":3,"ul_tx":3,"dl_retx":10,"ul_retx":1,"pucch1_snr":4,"pusch1_snr":10,"epre":6,"dl_mcs":3,"ul_mcs":1,"turbo_decoder_min":8,"turbo_decoder_avg":8,"turbo_decoder_max":5,"cqi":10,"ri":5}]}],"mongo_time":"2021-06-24T09:14:04.434Z","__v":0},{"_id":"60d44cdd8692f219bca1ed3c","time":3,"uplink":3,"downlink":0,"ue_list":[{"_id":"60d44cdd8692f219bca1ed3d","enb_ue_id":0,"mme_ue_id":2,"rnti":2,"cells":[{"_id":"60d44cdd8692f219bca1ed3e","cell_id":0,"dl_bitrate":0,"ul_bitrate":9,"dl_tx":0,"ul_tx":2,"dl_retx":2,"ul_retx":1,"pucch1_snr":9,"pusch1_snr":8,"epre":10,"dl_mcs":3,"ul_mcs":9,"turbo_decoder_min":7,"turbo_decoder_avg":5,"turbo_decoder_max":4,"cqi":8,"ri":10},{"_id":"60d44cdd8692f219bca1ed3f","cell_id":0,"dl_bitrate":6,"ul_bitrate":6,"dl_tx":5,"ul_tx":9,"dl_retx":3,"ul_retx":5,"pucch1_snr":3,"pusch1_snr":5,"epre":8,"dl_mcs":8,"ul_mcs":2,"turbo_decoder_min":5,"turbo_decoder_avg":3,"turbo_decoder_max":10,"cqi":10,"ri":10},{"_id":"60d44cdd8692f219bca1ed40","cell_id":2,"dl_bitrate":8,"ul_bitrate":0,"dl_tx":2,"ul_tx":8,"dl_retx":5,"ul_retx":5,"pucch1_snr":6,"pusch1_snr":3,"epre":10,"dl_mcs":2,"ul_mcs":4,"turbo_decoder_min":5,"turbo_decoder_avg":2,"turbo_decoder_max":1,"cqi":6,"ri":0}]},{"_id":"60d44cdd8692f219bca1ed41","enb_ue_id":2,"mme_ue_id":1,"rnti":1,"cells":[{"_id":"60d44cdd8692f219bca1ed42","cell_id":0,"dl_bitrate":3,"ul_bitrate":3,"dl_tx":8,"ul_tx":10,"dl_retx":5,"ul_retx":5,"pucch1_snr":3,"pusch1_snr":1,"epre":6,"dl_mcs":8,"ul_mcs":5,"turbo_decoder_min":4,"turbo_decoder_avg":1,"turbo_decoder_max":10,"cqi":4,"ri":2},{"_id":"60d44cdd8692f219bca1ed43","cell_id":1,"dl_bitrate":9,"ul_bitrate":3,"dl_tx":0,"ul_tx":3,"dl_retx":4,"ul_retx":3,"pucch1_snr":8,"pusch1_snr":7,"epre":10,"dl_mcs":8,"ul_mcs":1,"turbo_decoder_min":5,"turbo_decoder_avg":6,"turbo_decoder_max":9,"cqi":3,"ri":9},{"_id":"60d44cdd8692f219bca1ed44","cell_id":2,"dl_bitrate":5,"ul_bitrate":6,"dl_tx":2,"ul_tx":4,"dl_retx":5,"ul_retx":5,"pucch1_snr":1,"pusch1_snr":5,"epre":2,"dl_mcs":10,"ul_mcs":9,"turbo_decoder_min":0,"turbo_decoder_avg":0,"turbo_decoder_max":7,"cqi":10,"ri":1}]}],"mongo_time":"2021-06-24T09:14:05.442Z","__v":0},{"_id":"60d44cde8692f219bca1ed46","time":9,"uplink":0,"downlink":6,"ue_list":[{"_id":"60d44cde8692f219bca1ed47","enb_ue_id":1,"mme_ue_id":0,"rnti":0,"cells":[{"_id":"60d44cde8692f219bca1ed48","cell_id":1,"dl_bitrate":1,"ul_bitrate":1,"dl_tx":3,"ul_tx":2,"dl_retx":9,"ul_retx":3,"pucch1_snr":9,"pusch1_snr":0,"epre":10,"dl_mcs":5,"ul_mcs":4,"turbo_decoder_min":7,"turbo_decoder_avg":2,"turbo_decoder_max":8,"cqi":1,"ri":5},{"_id":"60d44cde8692f219bca1ed49","cell_id":0,"dl_bitrate":10,"ul_bitrate":10,"dl_tx":7,"ul_tx":6,"dl_retx":4,"ul_retx":7,"pucch1_snr":4,"pusch1_snr":6,"epre":1,"dl_mcs":2,"ul_mcs":0,"turbo_decoder_min":7,"turbo_decoder_avg":5,"turbo_decoder_max":1,"cqi":0,"ri":0},{"_id":"60d44cde8692f219bca1ed4a","cell_id":2,"dl_bitrate":9,"ul_bitrate":4,"dl_tx":4,"ul_tx":8,"dl_retx":9,"ul_retx":0,"pucch1_snr":5,"pusch1_snr":5,"epre":1,"dl_mcs":3,"ul_mcs":8,"turbo_decoder_min":2,"turbo_decoder_avg":6,"turbo_decoder_max":0,"cqi":8,"ri":7}]},{"_id":"60d44cde8692f219bca1ed4b","enb_ue_id":1,"mme_ue_id":2,"rnti":2,"cells":[{"_id":"60d44cde8692f219bca1ed4c","cell_id":2,"dl_bitrate":4,"ul_bitrate":6,"dl_tx":9,"ul_tx":5,"dl_retx":7,"ul_retx":5,"pucch1_snr":2,"pusch1_snr":3,"epre":0,"dl_mcs":1,"ul_mcs":10,"turbo_decoder_min":3,"turbo_decoder_avg":8,"turbo_decoder_max":9,"cqi":5,"ri":7},{"_id":"60d44cde8692f219bca1ed4d","cell_id":0,"dl_bitrate":6,"ul_bitrate":6,"dl_tx":8,"ul_tx":2,"dl_retx":10,"ul_retx":4,"pucch1_snr":8,"pusch1_snr":7,"epre":5,"dl_mcs":6,"ul_mcs":1,"turbo_decoder_min":8,"turbo_decoder_avg":2,"turbo_decoder_max":8,"cqi":3,"ri":10},{"_id":"60d44cde8692f219bca1ed4e","cell_id":0,"dl_bitrate":5,"ul_bitrate":0,"dl_tx":3,"ul_tx":10,"dl_retx":5,"ul_retx":9,"pucch1_snr":1,"pusch1_snr":3,"epre":8,"dl_mcs":1,"ul_mcs":1,"turbo_decoder_min":6,"turbo_decoder_avg":9,"turbo_decoder_max":6,"cqi":8,"ri":5}]}],"mongo_time":"2021-06-24T09:14:06.384Z","__v":0},{"_id":"60d44cde8692f219bca1ed50","time":7,"uplink":9,"downlink":3,"ue_list":[{"_id":"60d44cde8692f219bca1ed51","enb_ue_id":2,"mme_ue_id":0,"rnti":0,"cells":[{"_id":"60d44cde8692f219bca1ed52","cell_id":2,"dl_bitrate":8,"ul_bitrate":5,"dl_tx":4,"ul_tx":0,"dl_retx":9,"ul_retx":7,"pucch1_snr":6,"pusch1_snr":0,"epre":8,"dl_mcs":0,"ul_mcs":1,"turbo_decoder_min":3,"turbo_decoder_avg":10,"turbo_decoder_max":6,"cqi":8,"ri":4},{"_id":"60d44cde8692f219bca1ed53","cell_id":2,"dl_bitrate":1,"ul_bitrate":6,"dl_tx":6,"ul_tx":4,"dl_retx":2,"ul_retx":7,"pucch1_snr":7,"pusch1_snr":5,"epre":0,"dl_mcs":0,"ul_mcs":8,"turbo_decoder_min":2,"turbo_decoder_avg":10,"turbo_decoder_max":9,"cqi":8,"ri":4},{"_id":"60d44cde8692f219bca1ed54","cell_id":0,"dl_bitrate":0,"ul_bitrate":1,"dl_tx":6,"ul_tx":8,"dl_retx":1,"ul_retx":10,"pucch1_snr":1,"pusch1_snr":1,"epre":10,"dl_mcs":2,"ul_mcs":10,"turbo_decoder_min":10,"turbo_decoder_avg":2,"turbo_decoder_max":6,"cqi":5,"ri":7}]},{"_id":"60d44cde8692f219bca1ed55","enb_ue_id":0,"mme_ue_id":1,"rnti":0,"cells":[{"_id":"60d44cde8692f219bca1ed56","cell_id":2,"dl_bitrate":3,"ul_bitrate":1,"dl_tx":4,"ul_tx":5,"dl_retx":5,"ul_retx":7,"pucch1_snr":5,"pusch1_snr":4,"epre":10,"dl_mcs":4,"ul_mcs":10,"turbo_decoder_min":1,"turbo_decoder_avg":9,"turbo_decoder_max":0,"cqi":1,"ri":8},{"_id":"60d44cde8692f219bca1ed57","cell_id":1,"dl_bitrate":1,"ul_bitrate":3,"dl_tx":1,"ul_tx":7,"dl_retx":1,"ul_retx":5,"pucch1_snr":2,"pusch1_snr":6,"epre":3,"dl_mcs":2,"ul_mcs":2,"turbo_decoder_min":7,"turbo_decoder_avg":1,"turbo_decoder_max":9,"cqi":8,"ri":10},{"_id":"60d44cde8692f219bca1ed58","cell_id":0,"dl_bitrate":1,"ul_bitrate":6,"dl_tx":4,"ul_tx":5,"dl_retx":8,"ul_retx":5,"pucch1_snr":1,"pusch1_snr":1,"epre":5,"dl_mcs":5,"ul_mcs":9,"turbo_decoder_min":3,"turbo_decoder_avg":6,"turbo_decoder_max":8,"cqi":2,"ri":2}]}],"mongo_time":"2021-06-24T09:14:06.448Z","__v":0},{"_id":"60d44cdf8692f219bca1ed5a","time":3,"uplink":5,"downlink":0,"ue_list":[{"_id":"60d44cdf8692f219bca1ed5b","enb_ue_id":0,"mme_ue_id":0,"rnti":0,"cells":[{"_id":"60d44cdf8692f219bca1ed5c","cell_id":0,"dl_bitrate":7,"ul_bitrate":8,"dl_tx":3,"ul_tx":1,"dl_retx":5,"ul_retx":7,"pucch1_snr":7,"pusch1_snr":0,"epre":6,"dl_mcs":5,"ul_mcs":5,"turbo_decoder_min":5,"turbo_decoder_avg":8,"turbo_decoder_max":8,"cqi":8,"ri":6},{"_id":"60d44cdf8692f219bca1ed5d","cell_id":1,"dl_bitrate":10,"ul_bitrate":10,"dl_tx":6,"ul_tx":10,"dl_retx":1,"ul_retx":9,"pucch1_snr":7,"pusch1_snr":8,"epre":1,"dl_mcs":3,"ul_mcs":6,"turbo_decoder_min":7,"turbo_decoder_avg":2,"turbo_decoder_max":7,"cqi":8,"ri":10},{"_id":"60d44cdf8692f219bca1ed5e","cell_id":1,"dl_bitrate":8,"ul_bitrate":0,"dl_tx":2,"ul_tx":0,"dl_retx":0,"ul_retx":3,"pucch1_snr":9,"pusch1_snr":4,"epre":5,"dl_mcs":5,"ul_mcs":0,"turbo_decoder_min":2,"turbo_decoder_avg":4,"turbo_decoder_max":6,"cqi":5,"ri":5}]},{"_id":"60d44cdf8692f219bca1ed5f","enb_ue_id":1,"mme_ue_id":1,"rnti":2,"cells":[{"_id":"60d44cdf8692f219bca1ed60","cell_id":1,"dl_bitrate":10,"ul_bitrate":6,"dl_tx":6,"ul_tx":3,"dl_retx":10,"ul_retx":10,"pucch1_snr":7,"pusch1_snr":0,"epre":2,"dl_mcs":1,"ul_mcs":7,"turbo_decoder_min":8,"turbo_decoder_avg":8,"turbo_decoder_max":4,"cqi":8,"ri":1},{"_id":"60d44cdf8692f219bca1ed61","cell_id":0,"dl_bitrate":4,"ul_bitrate":0,"dl_tx":4,"ul_tx":4,"dl_retx":6,"ul_retx":8,"pucch1_snr":3,"pusch1_snr":3,"epre":1,"dl_mcs":10,"ul_mcs":3,"turbo_decoder_min":5,"turbo_decoder_avg":10,"turbo_decoder_max":9,"cqi":9,"ri":1},{"_id":"60d44cdf8692f219bca1ed62","cell_id":1,"dl_bitrate":6,"ul_bitrate":3,"dl_tx":10,"ul_tx":4,"dl_retx":1,"ul_retx":0,"pucch1_snr":1,"pusch1_snr":10,"epre":10,"dl_mcs":8,"ul_mcs":4,"turbo_decoder_min":9,"turbo_decoder_avg":2,"turbo_decoder_max":5,"cqi":3,"ri":3}]}],"mongo_time":"2021-06-24T09:14:07.404Z","__v":0},{"_id":"60d44cdf8692f219bca1ed64","time":4,"uplink":8,"downlink":2,"ue_list":[{"_id":"60d44cdf8692f219bca1ed65","enb_ue_id":2,"mme_ue_id":0,"rnti":2,"cells":[{"_id":"60d44cdf8692f219bca1ed66","cell_id":1,"dl_bitrate":9,"ul_bitrate":9,"dl_tx":4,"ul_tx":7,"dl_retx":6,"ul_retx":4,"pucch1_snr":5,"pusch1_snr":6,"epre":4,"dl_mcs":1,"ul_mcs":5,"turbo_decoder_min":3,"turbo_decoder_avg":4,"turbo_decoder_max":8,"cqi":8,"ri":2},{"_id":"60d44cdf8692f219bca1ed67","cell_id":0,"dl_bitrate":10,"ul_bitrate":10,"dl_tx":3,"ul_tx":3,"dl_retx":0,"ul_retx":9,"pucch1_snr":10,"pusch1_snr":3,"epre":4,"dl_mcs":1,"ul_mcs":1,"turbo_decoder_min":4,"turbo_decoder_avg":0,"turbo_decoder_max":8,"cqi":8,"ri":7},{"_id":"60d44cdf8692f219bca1ed68","cell_id":1,"dl_bitrate":7,"ul_bitrate":1,"dl_tx":1,"ul_tx":3,"dl_retx":6,"ul_retx":2,"pucch1_snr":5,"pusch1_snr":1,"epre":8,"dl_mcs":7,"ul_mcs":6,"turbo_decoder_min":2,"turbo_decoder_avg":2,"turbo_decoder_max":1,"cqi":9,"ri":10}]},{"_id":"60d44cdf8692f219bca1ed69","enb_ue_id":0,"mme_ue_id":2,"rnti":2,"cells":[{"_id":"60d44cdf8692f219bca1ed6a","cell_id":1,"dl_bitrate":3,"ul_bitrate":7,"dl_tx":1,"ul_tx":5,"dl_retx":6,"ul_retx":2,"pucch1_snr":9,"pusch1_snr":10,"epre":5,"dl_mcs":7,"ul_mcs":8,"turbo_decoder_min":5,"turbo_decoder_avg":5,"turbo_decoder_max":9,"cqi":6,"ri":8},{"_id":"60d44cdf8692f219bca1ed6b","cell_id":0,"dl_bitrate":0,"ul_bitrate":3,"dl_tx":5,"ul_tx":1,"dl_retx":1,"ul_retx":8,"pucch1_snr":9,"pusch1_snr":7,"epre":10,"dl_mcs":2,"ul_mcs":3,"turbo_decoder_min":10,"turbo_decoder_avg":4,"turbo_decoder_max":9,"cqi":5,"ri":3},{"_id":"60d44cdf8692f219bca1ed6c","cell_id":0,"dl_bitrate":8,"ul_bitrate":7,"dl_tx":3,"ul_tx":1,"dl_retx":1,"ul_retx":10,"pucch1_snr":9,"pusch1_snr":0,"epre":7,"dl_mcs":4,"ul_mcs":5,"turbo_decoder_min":2,"turbo_decoder_avg":9,"turbo_decoder_max":6,"cqi":1,"ri":9}]}],"mongo_time":"2021-06-24T09:14:07.467Z","__v":0},{"_id":"60d44ce08692f219bca1ed6e","time":8,"uplink":8,"downlink":5,"ue_list":[{"_id":"60d44ce08692f219bca1ed6f","enb_ue_id":2,"mme_ue_id":0,"rnti":2,"cells":[{"_id":"60d44ce08692f219bca1ed70","cell_id":0,"dl_bitrate":3,"ul_bitrate":1,"dl_tx":5,"ul_tx":9,"dl_retx":1,"ul_retx":8,"pucch1_snr":4,"pusch1_snr":3,"epre":3,"dl_mcs":10,"ul_mcs":7,"turbo_decoder_min":9,"turbo_decoder_avg":10,"turbo_decoder_max":6,"cqi":2,"ri":6},{"_id":"60d44ce08692f219bca1ed71","cell_id":1,"dl_bitrate":8,"ul_bitrate":1,"dl_tx":6,"ul_tx":2,"dl_retx":6,"ul_retx":10,"pucch1_snr":9,"pusch1_snr":1,"epre":7,"dl_mcs":9,"ul_mcs":9,"turbo_decoder_min":10,"turbo_decoder_avg":7,"turbo_decoder_max":6,"cqi":0,"ri":10},{"_id":"60d44ce08692f219bca1ed72","cell_id":0,"dl_bitrate":3,"ul_bitrate":6,"dl_tx":8,"ul_tx":5,"dl_retx":2,"ul_retx":9,"pucch1_snr":9,"pusch1_snr":6,"epre":4,"dl_mcs":3,"ul_mcs":9,"turbo_decoder_min":2,"turbo_decoder_avg":10,"turbo_decoder_max":9,"cqi":1,"ri":7}]},{"_id":"60d44ce08692f219bca1ed73","enb_ue_id":1,"mme_ue_id":1,"rnti":0,"cells":[{"_id":"60d44ce08692f219bca1ed74","cell_id":2,"dl_bitrate":10,"ul_bitrate":3,"dl_tx":2,"ul_tx":8,"dl_retx":8,"ul_retx":4,"pucch1_snr":2,"pusch1_snr":6,"epre":7,"dl_mcs":3,"ul_mcs":1,"turbo_decoder_min":4,"turbo_decoder_avg":0,"turbo_decoder_max":1,"cqi":5,"ri":4},{"_id":"60d44ce08692f219bca1ed75","cell_id":0,"dl_bitrate":0,"ul_bitrate":5,"dl_tx":9,"ul_tx":2,"dl_retx":0,"ul_retx":5,"pucch1_snr":3,"pusch1_snr":1,"epre":7,"dl_mcs":3,"ul_mcs":1,"turbo_decoder_min":7,"turbo_decoder_avg":6,"turbo_decoder_max":4,"cqi":6,"ri":9},{"_id":"60d44ce08692f219bca1ed76","cell_id":1,"dl_bitrate":8,"ul_bitrate":3,"dl_tx":6,"ul_tx":5,"dl_retx":0,"ul_retx":2,"pucch1_snr":10,"pusch1_snr":6,"epre":8,"dl_mcs":10,"ul_mcs":4,"turbo_decoder_min":3,"turbo_decoder_avg":8,"turbo_decoder_max":6,"cqi":6,"ri":8}]}],"mongo_time":"2021-06-24T09:14:08.414Z","__v":0},{"_id":"60d44ce08692f219bca1ed78","time":8,"uplink":8,"downlink":5,"ue_list":[{"_id":"60d44ce08692f219bca1ed79","enb_ue_id":2,"mme_ue_id":1,"rnti":2,"cells":[{"_id":"60d44ce08692f219bca1ed7a","cell_id":1,"dl_bitrate":5,"ul_bitrate":5,"dl_tx":2,"ul_tx":2,"dl_retx":9,"ul_retx":8,"pucch1_snr":2,"pusch1_snr":4,"epre":5,"dl_mcs":8,"ul_mcs":10,"turbo_decoder_min":8,"turbo_decoder_avg":9,"turbo_decoder_max":2,"cqi":0,"ri":9},{"_id":"60d44ce08692f219bca1ed7b","cell_id":1,"dl_bitrate":9,"ul_bitrate":0,"dl_tx":7,"ul_tx":1,"dl_retx":0,"ul_retx":4,"pucch1_snr":10,"pusch1_snr":7,"epre":9,"dl_mcs":9,"ul_mcs":3,"turbo_decoder_min":6,"turbo_decoder_avg":0,"turbo_decoder_max":1,"cqi":7,"ri":9},{"_id":"60d44ce08692f219bca1ed7c","cell_id":0,"dl_bitrate":1,"ul_bitrate":5,"dl_tx":7,"ul_tx":3,"dl_retx":2,"ul_retx":4,"pucch1_snr":9,"pusch1_snr":0,"epre":10,"dl_mcs":8,"ul_mcs":9,"turbo_decoder_min":8,"turbo_decoder_avg":2,"turbo_decoder_max":10,"cqi":10,"ri":4}]},{"_id":"60d44ce08692f219bca1ed7d","enb_ue_id":0,"mme_ue_id":1,"rnti":2,"cells":[{"_id":"60d44ce08692f219bca1ed7e","cell_id":2,"dl_bitrate":4,"ul_bitrate":0,"dl_tx":3,"ul_tx":2,"dl_retx":1,"ul_retx":9,"pucch1_snr":7,"pusch1_snr":2,"epre":1,"dl_mcs":0,"ul_mcs":7,"turbo_decoder_min":7,"turbo_decoder_avg":7,"turbo_decoder_max":10,"cqi":8,"ri":10},{"_id":"60d44ce08692f219bca1ed7f","cell_id":0,"dl_bitrate":5,"ul_bitrate":5,"dl_tx":5,"ul_tx":3,"dl_retx":8,"ul_retx":4,"pucch1_snr":5,"pusch1_snr":9,"epre":9,"dl_mcs":5,"ul_mcs":1,"turbo_decoder_min":0,"turbo_decoder_avg":4,"turbo_decoder_max":6,"cqi":10,"ri":5},{"_id":"60d44ce08692f219bca1ed80","cell_id":2,"dl_bitrate":0,"ul_bitrate":0,"dl_tx":6,"ul_tx":8,"dl_retx":4,"ul_retx":2,"pucch1_snr":2,"pusch1_snr":0,"epre":6,"dl_mcs":0,"ul_mcs":6,"turbo_decoder_min":1,"turbo_decoder_avg":8,"turbo_decoder_max":0,"cqi":10,"ri":5}]}],"mongo_time":"2021-06-24T09:14:08.482Z","__v":0},{"_id":"60d44ce18692f219bca1ed82","time":0,"uplink":0,"downlink":3,"ue_list":[{"_id":"60d44ce18692f219bca1ed83","enb_ue_id":1,"mme_ue_id":0,"rnti":1,"cells":[{"_id":"60d44ce18692f219bca1ed84","cell_id":0,"dl_bitrate":6,"ul_bitrate":10,"dl_tx":8,"ul_tx":1,"dl_retx":3,"ul_retx":10,"pucch1_snr":10,"pusch1_snr":10,"epre":5,"dl_mcs":2,"ul_mcs":0,"turbo_decoder_min":1,"turbo_decoder_avg":1,"turbo_decoder_max":10,"cqi":5,"ri":0},{"_id":"60d44ce18692f219bca1ed85","cell_id":0,"dl_bitrate":6,"ul_bitrate":6,"dl_tx":6,"ul_tx":1,"dl_retx":10,"ul_retx":8,"pucch1_snr":10,"pusch1_snr":3,"epre":4,"dl_mcs":7,"ul_mcs":10,"turbo_decoder_min":1,"turbo_decoder_avg":6,"turbo_decoder_max":2,"cqi":4,"ri":7},{"_id":"60d44ce18692f219bca1ed86","cell_id":2,"dl_bitrate":8,"ul_bitrate":0,"dl_tx":3,"ul_tx":1,"dl_retx":10,"ul_retx":4,"pucch1_snr":5,"pusch1_snr":4,"epre":3,"dl_mcs":7,"ul_mcs":4,"turbo_decoder_min":0,"turbo_decoder_avg":7,"turbo_decoder_max":5,"cqi":9,"ri":8}]},{"_id":"60d44ce18692f219bca1ed87","enb_ue_id":1,"mme_ue_id":0,"rnti":1,"cells":[{"_id":"60d44ce18692f219bca1ed88","cell_id":2,"dl_bitrate":5,"ul_bitrate":9,"dl_tx":9,"ul_tx":1,"dl_retx":10,"ul_retx":10,"pucch1_snr":10,"pusch1_snr":10,"epre":9,"dl_mcs":9,"ul_mcs":6,"turbo_decoder_min":4,"turbo_decoder_avg":2,"turbo_decoder_max":6,"cqi":5,"ri":5},{"_id":"60d44ce18692f219bca1ed89","cell_id":1,"dl_bitrate":2,"ul_bitrate":4,"dl_tx":9,"ul_tx":1,"dl_retx":7,"ul_retx":0,"pucch1_snr":6,"pusch1_snr":1,"epre":8,"dl_mcs":1,"ul_mcs":9,"turbo_decoder_min":6,"turbo_decoder_avg":5,"turbo_decoder_max":7,"cqi":8,"ri":1},{"_id":"60d44ce18692f219bca1ed8a","cell_id":0,"dl_bitrate":1,"ul_bitrate":1,"dl_tx":10,"ul_tx":10,"dl_retx":7,"ul_retx":8,"pucch1_snr":2,"pusch1_snr":8,"epre":1,"dl_mcs":2,"ul_mcs":6,"turbo_decoder_min":4,"turbo_decoder_avg":4,"turbo_decoder_max":10,"cqi":1,"ri":4}]}],"mongo_time":"2021-06-24T09:14:09.424Z","__v":0},{"_id":"60d44ce18692f219bca1ed8c","time":1,"uplink":10,"downlink":0,"ue_list":[{"_id":"60d44ce18692f219bca1ed8d","enb_ue_id":1,"mme_ue_id":2,"rnti":1,"cells":[{"_id":"60d44ce18692f219bca1ed8e","cell_id":2,"dl_bitrate":4,"ul_bitrate":6,"dl_tx":2,"ul_tx":8,"dl_retx":1,"ul_retx":3,"pucch1_snr":5,"pusch1_snr":3,"epre":7,"dl_mcs":6,"ul_mcs":8,"turbo_decoder_min":6,"turbo_decoder_avg":9,"turbo_decoder_max":6,"cqi":7,"ri":4},{"_id":"60d44ce18692f219bca1ed8f","cell_id":1,"dl_bitrate":5,"ul_bitrate":6,"dl_tx":0,"ul_tx":8,"dl_retx":4,"ul_retx":3,"pucch1_snr":4,"pusch1_snr":3,"epre":0,"dl_mcs":0,"ul_mcs":10,"turbo_decoder_min":7,"turbo_decoder_avg":7,"turbo_decoder_max":2,"cqi":5,"ri":6},{"_id":"60d44ce18692f219bca1ed90","cell_id":1,"dl_bitrate":0,"ul_bitrate":0,"dl_tx":5,"ul_tx":4,"dl_retx":7,"ul_retx":5,"pucch1_snr":9,"pusch1_snr":7,"epre":3,"dl_mcs":6,"ul_mcs":2,"turbo_decoder_min":8,"turbo_decoder_avg":10,"turbo_decoder_max":0,"cqi":3,"ri":8}]},{"_id":"60d44ce18692f219bca1ed91","enb_ue_id":0,"mme_ue_id":1,"rnti":1,"cells":[{"_id":"60d44ce18692f219bca1ed92","cell_id":1,"dl_bitrate":3,"ul_bitrate":6,"dl_tx":7,"ul_tx":3,"dl_retx":3,"ul_retx":4,"pucch1_snr":3,"pusch1_snr":3,"epre":10,"dl_mcs":7,"ul_mcs":3,"turbo_decoder_min":6,"turbo_decoder_avg":0,"turbo_decoder_max":0,"cqi":3,"ri":0},{"_id":"60d44ce18692f219bca1ed93","cell_id":2,"dl_bitrate":3,"ul_bitrate":7,"dl_tx":1,"ul_tx":7,"dl_retx":6,"ul_retx":3,"pucch1_snr":1,"pusch1_snr":10,"epre":2,"dl_mcs":4,"ul_mcs":5,"turbo_decoder_min":1,"turbo_decoder_avg":7,"turbo_decoder_max":4,"cqi":1,"ri":3},{"_id":"60d44ce18692f219bca1ed94","cell_id":2,"dl_bitrate":0,"ul_bitrate":4,"dl_tx":5,"ul_tx":6,"dl_retx":10,"ul_retx":1,"pucch1_snr":8,"pusch1_snr":8,"epre":8,"dl_mcs":10,"ul_mcs":1,"turbo_decoder_min":1,"turbo_decoder_avg":1,"turbo_decoder_max":8,"cqi":4,"ri":8}]}],"mongo_time":"2021-06-24T09:14:09.487Z","__v":0},{"_id":"60d44ce28692f219bca1ed96","time":8,"uplink":4,"downlink":6,"ue_list":[{"_id":"60d44ce28692f219bca1ed97","enb_ue_id":1,"mme_ue_id":0,"rnti":0,"cells":[{"_id":"60d44ce28692f219bca1ed98","cell_id":0,"dl_bitrate":7,"ul_bitrate":1,"dl_tx":5,"ul_tx":8,"dl_retx":4,"ul_retx":10,"pucch1_snr":1,"pusch1_snr":6,"epre":8,"dl_mcs":1,"ul_mcs":8,"turbo_decoder_min":5,"turbo_decoder_avg":5,"turbo_decoder_max":1,"cqi":3,"ri":6},{"_id":"60d44ce28692f219bca1ed99","cell_id":1,"dl_bitrate":9,"ul_bitrate":2,"dl_tx":7,"ul_tx":0,"dl_retx":7,"ul_retx":0,"pucch1_snr":4,"pusch1_snr":3,"epre":9,"dl_mcs":9,"ul_mcs":9,"turbo_decoder_min":3,"turbo_decoder_avg":3,"turbo_decoder_max":5,"cqi":5,"ri":5},{"_id":"60d44ce28692f219bca1ed9a","cell_id":1,"dl_bitrate":4,"ul_bitrate":3,"dl_tx":0,"ul_tx":2,"dl_retx":2,"ul_retx":4,"pucch1_snr":9,"pusch1_snr":7,"epre":4,"dl_mcs":2,"ul_mcs":9,"turbo_decoder_min":2,"turbo_decoder_avg":10,"turbo_decoder_max":1,"cqi":3,"ri":8}]},{"_id":"60d44ce28692f219bca1ed9b","enb_ue_id":2,"mme_ue_id":0,"rnti":1,"cells":[{"_id":"60d44ce28692f219bca1ed9c","cell_id":0,"dl_bitrate":2,"ul_bitrate":10,"dl_tx":2,"ul_tx":2,"dl_retx":10,"ul_retx":6,"pucch1_snr":6,"pusch1_snr":7,"epre":8,"dl_mcs":10,"ul_mcs":8,"turbo_decoder_min":6,"turbo_decoder_avg":0,"turbo_decoder_max":2,"cqi":2,"ri":10},{"_id":"60d44ce28692f219bca1ed9d","cell_id":0,"dl_bitrate":2,"ul_bitrate":4,"dl_tx":4,"ul_tx":4,"dl_retx":9,"ul_retx":7,"pucch1_snr":8,"pusch1_snr":3,"epre":0,"dl_mcs":5,"ul_mcs":2,"turbo_decoder_min":9,"turbo_decoder_avg":0,"turbo_decoder_max":5,"cqi":10,"ri":0},{"_id":"60d44ce28692f219bca1ed9e","cell_id":0,"dl_bitrate":8,"ul_bitrate":3,"dl_tx":3,"ul_tx":3,"dl_retx":7,"ul_retx":10,"pucch1_snr":6,"pusch1_snr":5,"epre":8,"dl_mcs":8,"ul_mcs":7,"turbo_decoder_min":9,"turbo_decoder_avg":0,"turbo_decoder_max":10,"cqi":6,"ri":1}]}],"mongo_time":"2021-06-24T09:14:10.431Z","__v":0},{"_id":"60d44ce28692f219bca1eda0","time":5,"uplink":3,"downlink":5,"ue_list":[{"_id":"60d44ce28692f219bca1eda1","enb_ue_id":0,"mme_ue_id":2,"rnti":0,"cells":[{"_id":"60d44ce28692f219bca1eda2","cell_id":2,"dl_bitrate":6,"ul_bitrate":9,"dl_tx":0,"ul_tx":1,"dl_retx":9,"ul_retx":5,"pucch1_snr":3,"pusch1_snr":0,"epre":6,"dl_mcs":1,"ul_mcs":1,"turbo_decoder_min":5,"turbo_decoder_avg":5,"turbo_decoder_max":8,"cqi":1,"ri":1},{"_id":"60d44ce28692f219bca1eda3","cell_id":2,"dl_bitrate":3,"ul_bitrate":4,"dl_tx":4,"ul_tx":3,"dl_retx":8,"ul_retx":1,"pucch1_snr":9,"pusch1_snr":10,"epre":6,"dl_mcs":5,"ul_mcs":6,"turbo_decoder_min":10,"turbo_decoder_avg":0,"turbo_decoder_max":1,"cqi":2,"ri":6},{"_id":"60d44ce28692f219bca1eda4","cell_id":1,"dl_bitrate":8,"ul_bitrate":2,"dl_tx":5,"ul_tx":7,"dl_retx":8,"ul_retx":9,"pucch1_snr":4,"pusch1_snr":5,"epre":7,"dl_mcs":0,"ul_mcs":7,"turbo_decoder_min":3,"turbo_decoder_avg":9,"turbo_decoder_max":8,"cqi":6,"ri":8}]},{"_id":"60d44ce28692f219bca1eda5","enb_ue_id":0,"mme_ue_id":1,"rnti":2,"cells":[{"_id":"60d44ce28692f219bca1eda6","cell_id":0,"dl_bitrate":8,"ul_bitrate":7,"dl_tx":0,"ul_tx":8,"dl_retx":1,"ul_retx":10,"pucch1_snr":3,"pusch1_snr":7,"epre":1,"dl_mcs":4,"ul_mcs":3,"turbo_decoder_min":5,"turbo_decoder_avg":7,"turbo_decoder_max":0,"cqi":2,"ri":10},{"_id":"60d44ce28692f219bca1eda7","cell_id":1,"dl_bitrate":1,"ul_bitrate":2,"dl_tx":10,"ul_tx":7,"dl_retx":3,"ul_retx":9,"pucch1_snr":5,"pusch1_snr":10,"epre":0,"dl_mcs":7,"ul_mcs":0,"turbo_decoder_min":6,"turbo_decoder_avg":5,"turbo_decoder_max":5,"cqi":9,"ri":6},{"_id":"60d44ce28692f219bca1eda8","cell_id":1,"dl_bitrate":7,"ul_bitrate":4,"dl_tx":4,"ul_tx":1,"dl_retx":9,"ul_retx":4,"pucch1_snr":3,"pusch1_snr":5,"epre":1,"dl_mcs":1,"ul_mcs":1,"turbo_decoder_min":8,"turbo_decoder_avg":10,"turbo_decoder_max":1,"cqi":6,"ri":9}]}],"mongo_time":"2021-06-24T09:14:10.496Z","__v":0},{"_id":"60d44ce38692f219bca1edaa","time":5,"uplink":7,"downlink":4,"ue_list":[{"_id":"60d44ce38692f219bca1edab","enb_ue_id":2,"mme_ue_id":1,"rnti":0,"cells":[{"_id":"60d44ce38692f219bca1edac","cell_id":2,"dl_bitrate":2,"ul_bitrate":6,"dl_tx":8,"ul_tx":5,"dl_retx":5,"ul_retx":3,"pucch1_snr":3,"pusch1_snr":8,"epre":9,"dl_mcs":6,"ul_mcs":0,"turbo_decoder_min":3,"turbo_decoder_avg":7,"turbo_decoder_max":3,"cqi":3,"ri":1},{"_id":"60d44ce38692f219bca1edad","cell_id":2,"dl_bitrate":3,"ul_bitrate":0,"dl_tx":3,"ul_tx":0,"dl_retx":9,"ul_retx":5,"pucch1_snr":1,"pusch1_snr":8,"epre":8,"dl_mcs":5,"ul_mcs":3,"turbo_decoder_min":10,"turbo_decoder_avg":5,"turbo_decoder_max":8,"cqi":6,"ri":0},{"_id":"60d44ce38692f219bca1edae","cell_id":0,"dl_bitrate":8,"ul_bitrate":5,"dl_tx":1,"ul_tx":0,"dl_retx":8,"ul_retx":8,"pucch1_snr":0,"pusch1_snr":10,"epre":3,"dl_mcs":1,"ul_mcs":1,"turbo_decoder_min":8,"turbo_decoder_avg":6,"turbo_decoder_max":6,"cqi":1,"ri":10}]},{"_id":"60d44ce38692f219bca1edaf","enb_ue_id":2,"mme_ue_id":0,"rnti":2,"cells":[{"_id":"60d44ce38692f219bca1edb0","cell_id":1,"dl_bitrate":7,"ul_bitrate":6,"dl_tx":6,"ul_tx":3,"dl_retx":5,"ul_retx":6,"pucch1_snr":9,"pusch1_snr":6,"epre":10,"dl_mcs":6,"ul_mcs":6,"turbo_decoder_min":0,"turbo_decoder_avg":10,"turbo_decoder_max":5,"cqi":8,"ri":3},{"_id":"60d44ce38692f219bca1edb1","cell_id":0,"dl_bitrate":8,"ul_bitrate":10,"dl_tx":3,"ul_tx":10,"dl_retx":6,"ul_retx":5,"pucch1_snr":7,"pusch1_snr":4,"epre":4,"dl_mcs":10,"ul_mcs":5,"turbo_decoder_min":5,"turbo_decoder_avg":7,"turbo_decoder_max":8,"cqi":6,"ri":8},{"_id":"60d44ce38692f219bca1edb2","cell_id":2,"dl_bitrate":9,"ul_bitrate":7,"dl_tx":4,"ul_tx":2,"dl_retx":10,"ul_retx":1,"pucch1_snr":8,"pusch1_snr":9,"epre":9,"dl_mcs":5,"ul_mcs":9,"turbo_decoder_min":0,"turbo_decoder_avg":8,"turbo_decoder_max":5,"cqi":4,"ri":8}]}],"mongo_time":"2021-06-24T09:14:11.434Z","__v":0},{"_id":"60d44ce38692f219bca1edb4","time":10,"uplink":4,"downlink":7,"ue_list":[{"_id":"60d44ce38692f219bca1edb5","enb_ue_id":2,"mme_ue_id":0,"rnti":0,"cells":[{"_id":"60d44ce38692f219bca1edb6","cell_id":1,"dl_bitrate":8,"ul_bitrate":0,"dl_tx":4,"ul_tx":0,"dl_retx":5,"ul_retx":0,"pucch1_snr":2,"pusch1_snr":8,"epre":6,"dl_mcs":6,"ul_mcs":3,"turbo_decoder_min":5,"turbo_decoder_avg":6,"turbo_decoder_max":6,"cqi":7,"ri":7},{"_id":"60d44ce38692f219bca1edb7","cell_id":2,"dl_bitrate":9,"ul_bitrate":8,"dl_tx":9,"ul_tx":6,"dl_retx":8,"ul_retx":6,"pucch1_snr":3,"pusch1_snr":9,"epre":10,"dl_mcs":9,"ul_mcs":1,"turbo_decoder_min":9,"turbo_decoder_avg":8,"turbo_decoder_max":9,"cqi":10,"ri":2},{"_id":"60d44ce38692f219bca1edb8","cell_id":0,"dl_bitrate":4,"ul_bitrate":0,"dl_tx":2,"ul_tx":2,"dl_retx":3,"ul_retx":6,"pucch1_snr":2,"pusch1_snr":5,"epre":4,"dl_mcs":7,"ul_mcs":9,"turbo_decoder_min":10,"turbo_decoder_avg":3,"turbo_decoder_max":0,"cqi":7,"ri":1}]},{"_id":"60d44ce38692f219bca1edb9","enb_ue_id":1,"mme_ue_id":0,"rnti":2,"cells":[{"_id":"60d44ce38692f219bca1edba","cell_id":0,"dl_bitrate":5,"ul_bitrate":7,"dl_tx":3,"ul_tx":3,"dl_retx":4,"ul_retx":6,"pucch1_snr":0,"pusch1_snr":9,"epre":4,"dl_mcs":7,"ul_mcs":9,"turbo_decoder_min":4,"turbo_decoder_avg":6,"turbo_decoder_max":8,"cqi":1,"ri":3},{"_id":"60d44ce38692f219bca1edbb","cell_id":1,"dl_bitrate":8,"ul_bitrate":10,"dl_tx":1,"ul_tx":10,"dl_retx":0,"ul_retx":6,"pucch1_snr":8,"pusch1_snr":9,"epre":9,"dl_mcs":1,"ul_mcs":5,"turbo_decoder_min":3,"turbo_decoder_avg":6,"turbo_decoder_max":3,"cqi":4,"ri":5},{"_id":"60d44ce38692f219bca1edbc","cell_id":1,"dl_bitrate":9,"ul_bitrate":6,"dl_tx":7,"ul_tx":2,"dl_retx":10,"ul_retx":9,"pucch1_snr":6,"pusch1_snr":3,"epre":9,"dl_mcs":8,"ul_mcs":3,"turbo_decoder_min":1,"turbo_decoder_avg":7,"turbo_decoder_max":10,"cqi":8,"ri":7}]}],"mongo_time":"2021-06-24T09:14:11.504Z","__v":0}]